lyp_myserver_demo/__init__.py
lyp_myserver_demo-0.1.0.dist-info/METADATA
lyp_myserver_demo-0.1.0.dist-info/WHEEL
lyp_myserver_demo-0.1.0.dist-info/entry_points.txt
lyp_myserver_demo-0.1.0.dist-info/RECORD
