Metadata-Version: 2.4
Name: lyp-myserver-demo
Version: 0.1.0
Summary: Add your description here
Author-email: 卢雨芃 <k86359303@gmail.com>
Requires-Python: >=3.13
Requires-Dist: mcp[cli]>=1.25.0
